package_mongo/__init__.py
package_mongo/mongo_crud.py
packagemongo-0.0.2.dist-info/METADATA
packagemongo-0.0.2.dist-info/WHEEL
packagemongo-0.0.2.dist-info/top_level.txt
packagemongo-0.0.2.dist-info/RECORD
